pyonms/MANIFEST.in
pyonms/__init__.py
pyonms/dao/__init__.py
pyonms/dao/alarms.py
pyonms/dao/base.py
pyonms/dao/business_services.py
pyonms/dao/enlinkd.py
pyonms/dao/events.py
pyonms/dao/foreign_sources.py
pyonms/dao/health.py
pyonms/dao/info.py
pyonms/dao/ips.py
pyonms/dao/nodes.py
pyonms/dao/requisitions.py
pyonms/dao/udl.py
pyonms/models/__init__.py
pyonms/models/alarm.py
pyonms/models/business_service.py
pyonms/models/enlinkd.py
pyonms/models/event.py
pyonms/models/exceptions.py
pyonms/models/foreign_source.py
pyonms/models/health.py
pyonms/models/info.py
pyonms/models/node.py
pyonms/models/requisition.py
pyonms/models/udl.py
pyonms/utils/__init__.py
pyonms-0.1.3.dist-info/METADATA
pyonms-0.1.3.dist-info/WHEEL
pyonms-0.1.3.dist-info/licenses/LICENSE.txt
pyonms-0.1.3.dist-info/RECORD
