Metadata-Version: 2.1
Name: pyonms
Version: 0.1.3
Summary: A Python library for accessing the OpenNMS REST API.
Project-URL: Homepage, https://github.com/mmahacek/PyONMS
Project-URL: Documentation, https://mmahacek.github.io/PyONMS/
Project-URL: Changelog, https://github.com/mmahacek/PyONMS/blob/main/CHANGELOG.md
Author-email: Mark Mahacek <mmahacek@opennms.com>
License: MIT License
License-File: LICENSE.txt
Classifier: Development Status :: 3 - Alpha
Classifier: Intended Audience :: Developers
Classifier: Intended Audience :: Information Technology
Classifier: Intended Audience :: System Administrators
Classifier: License :: OSI Approved :: MIT License
Classifier: Natural Language :: English
Classifier: Operating System :: OS Independent
Classifier: Programming Language :: Python :: 3
Requires-Python: >=3.8
Requires-Dist: python-dotenv
Requires-Dist: requests
Requires-Dist: tqdm
Requires-Dist: xmltodict
